{
	"configurations" : 
	[
		{
			"directories" : 
			[
				{
					"build" : ".",
					"hasInstallRule" : true,
					"jsonFile" : "directory-.-Debug-84a375147682dadc826e.json",
					"minimumCMakeVersion" : 
					{
						"string" : "3.16"
					},
					"projectIndex" : 0,
					"source" : ".",
					"targetIndexes" : 
					[
						0,
						1,
						2,
						3,
						4,
						5,
						6,
						7,
						8,
						9,
						10,
						11,
						12,
						13,
						14,
						15
					]
				}
			],
			"name" : "Debug",
			"projects" : 
			[
				{
					"directoryIndexes" : 
					[
						0
					],
					"name" : "TextField",
					"targetIndexes" : 
					[
						0,
						1,
						2,
						3,
						4,
						5,
						6,
						7,
						8,
						9,
						10,
						11,
						12,
						13,
						14,
						15
					]
				}
			],
			"targets" : 
			[
				{
					"directoryIndex" : 0,
					"id" : "all_aotstats::@6890427a1f51a3e7e1df",
					"jsonFile" : "target-all_aotstats-Debug-619e0e4a18211ddb7394.json",
					"name" : "all_aotstats",
					"projectIndex" : 0
				},
				{
					"directoryIndex" : 0,
					"id" : "all_qmllint::@6890427a1f51a3e7e1df",
					"jsonFile" : "target-all_qmllint-Debug-c1690180541218a5a010.json",
					"name" : "all_qmllint",
					"projectIndex" : 0
				},
				{
					"directoryIndex" : 0,
					"id" : "all_qmllint_json::@6890427a1f51a3e7e1df",
					"jsonFile" : "target-all_qmllint_json-Debug-ee55b14344bb4c7ae04f.json",
					"name" : "all_qmllint_json",
					"projectIndex" : 0
				},
				{
					"directoryIndex" : 0,
					"id" : "all_qmllint_module::@6890427a1f51a3e7e1df",
					"jsonFile" : "target-all_qmllint_module-Debug-10df68da3ef09f9d09c5.json",
					"name" : "all_qmllint_module",
					"projectIndex" : 0
				},
				{
					"directoryIndex" : 0,
					"id" : "all_qmltyperegistrations::@6890427a1f51a3e7e1df",
					"jsonFile" : "target-all_qmltyperegistrations-Debug-9371d63af3119cf4d6e4.json",
					"name" : "all_qmltyperegistrations",
					"projectIndex" : 0
				},
				{
					"directoryIndex" : 0,
					"id" : "appTextField::@6890427a1f51a3e7e1df",
					"jsonFile" : "target-appTextField-Debug-0adda2c75eae9395bf30.json",
					"name" : "appTextField",
					"projectIndex" : 0
				},
				{
					"directoryIndex" : 0,
					"id" : "appTextField_autogen::@6890427a1f51a3e7e1df",
					"jsonFile" : "target-appTextField_autogen-Debug-a89b71ede2b247e019ae.json",
					"name" : "appTextField_autogen",
					"projectIndex" : 0
				},
				{
					"directoryIndex" : 0,
					"id" : "appTextField_autogen_timestamp_deps::@6890427a1f51a3e7e1df",
					"jsonFile" : "target-appTextField_autogen_timestamp_deps-Debug-eda64e2c9088b2cab4b2.json",
					"name" : "appTextField_autogen_timestamp_deps",
					"projectIndex" : 0
				},
				{
					"directoryIndex" : 0,
					"id" : "appTextField_copy_qml::@6890427a1f51a3e7e1df",
					"jsonFile" : "target-appTextField_copy_qml-Debug-3d126d1e9f7e5a0471ee.json",
					"name" : "appTextField_copy_qml",
					"projectIndex" : 0
				},
				{
					"directoryIndex" : 0,
					"id" : "appTextField_copy_res::@6890427a1f51a3e7e1df",
					"jsonFile" : "target-appTextField_copy_res-Debug-defe36b8489daa90a68e.json",
					"name" : "appTextField_copy_res",
					"projectIndex" : 0
				},
				{
					"directoryIndex" : 0,
					"id" : "appTextField_qmlimportscan::@6890427a1f51a3e7e1df",
					"jsonFile" : "target-appTextField_qmlimportscan-Debug-ccf7505e4674f30f7b8f.json",
					"name" : "appTextField_qmlimportscan",
					"projectIndex" : 0
				},
				{
					"directoryIndex" : 0,
					"id" : "appTextField_qmllint::@6890427a1f51a3e7e1df",
					"jsonFile" : "target-appTextField_qmllint-Debug-39b01111b7b0aae352ac.json",
					"name" : "appTextField_qmllint",
					"projectIndex" : 0
				},
				{
					"directoryIndex" : 0,
					"id" : "appTextField_qmllint_json::@6890427a1f51a3e7e1df",
					"jsonFile" : "target-appTextField_qmllint_json-Debug-19d0b1249c455782e446.json",
					"name" : "appTextField_qmllint_json",
					"projectIndex" : 0
				},
				{
					"directoryIndex" : 0,
					"id" : "appTextField_qmllint_module::@6890427a1f51a3e7e1df",
					"jsonFile" : "target-appTextField_qmllint_module-Debug-d4754531bc45a559840e.json",
					"name" : "appTextField_qmllint_module",
					"projectIndex" : 0
				},
				{
					"directoryIndex" : 0,
					"id" : "appTextField_qmltyperegistration::@6890427a1f51a3e7e1df",
					"jsonFile" : "target-appTextField_qmltyperegistration-Debug-fe977703c2d63c6fa82f.json",
					"name" : "appTextField_qmltyperegistration",
					"projectIndex" : 0
				},
				{
					"directoryIndex" : 0,
					"id" : "module_appTextField_aotstats_target::@6890427a1f51a3e7e1df",
					"jsonFile" : "target-module_appTextField_aotstats_target-Debug-366e9bf361006888cd48.json",
					"name" : "module_appTextField_aotstats_target",
					"projectIndex" : 0
				}
			]
		}
	],
	"kind" : "codemodel",
	"paths" : 
	{
		"build" : "/home/girish-v-b/CPP/CodeBugs/TextField/build/GirishKit-Debug",
		"source" : "/home/girish-v-b/CPP/CodeBugs/TextField"
	},
	"version" : 
	{
		"major" : 2,
		"minor" : 7
	}
}
